{"cameraMode":{"drawMode":0,"name":"Shaded","section":"Shading Mode"},"sceneLighting":true,"audioPlay":false,"sceneViewState":{"m_AlwaysRefresh":false,"showFog":false,"showSkybox":true,"showFlares":true,"showImageEffects":false,"showParticleSystems":true,"showVisualEffectGraphs":true,"m_FxEnabled":true},"in2DMode":false,"pivot":{"x":87.76129913330078,"y":13.058862686157227,"z":39.145652770996097},"rotation":{"x":-0.14899811148643495,"y":-0.7346618175506592,"z":0.6406115889549255,"w":-0.1682470440864563},"size":5.048712253570557,"orthographic":false}